f2format.py
python_f2format-0.8.4.dist-info/LICENSE
python_f2format-0.8.4.dist-info/METADATA
python_f2format-0.8.4.dist-info/WHEEL
python_f2format-0.8.4.dist-info/entry_points.txt
python_f2format-0.8.4.dist-info/top_level.txt
python_f2format-0.8.4.dist-info/zip-safe
python_f2format-0.8.4.dist-info/RECORD
